[
 {
  "table":"DDTYPES",
  "data":
  [
   {
    "TYPENAME":"ZCL_ETR_INVOICE_SAVE_JOB",
    "STATE":"A",
    "TYPEKIND":"CLAS"
   }
  ]
 },
 {
  "table":"SEOCLASS",
  "data":
  [
   {
    "CLSNAME":"ZCL_ETR_INVOICE_SAVE_JOB",
    "CLSTYPE":0,
    "UUID":"wcxnZTdNHu+kxnShNxWiTA==",
    "REMOTE":""
   }
  ]
 },
 {
  "table":"SEOCLASSDF",
  "data":
  [
   {
    "CLSNAME":"ZCL_ETR_INVOICE_SAVE_JOB",
    "VERSION":1,
    "CATEGORY":0,
    "EXPOSURE":2,
    "STATE":1,
    "RELEASE":0,
    "AUTHOR":"",
    "CREATEDON":"2024-10-24",
    "CHANGEDBY":"",
    "CHANGEDON":"0000-00-00",
    "CHGDANYBY":"",
    "CHGDANYON":"0000-00-00",
    "CLSEMBED":"",
    "CLSABSTRCT":"",
    "CLSFINAL":"X",
    "CLSCCINCL":"X",
    "CLSDEFATT":"",
    "CLSDEFMTD":"",
    "REFCLSNAME":"",
    "FIXPT":"X",
    "VARCL":"",
    "UNICODE":"5",
    "RSTAT":"",
    "CLSBCIMPL":"",
    "R3RELEASE":"912",
    "CLSBCTRANS":"",
    "CLSBCCAT":0,
    "CLSBCNODEL":"",
    "CLSADDON":"",
    "MSG_ID":"",
    "CLSPROXY":"",
    "CLSSHAREDMEMORY":"",
    "WITH_UNIT_TESTS":"X",
    "DURATION_TYPE":"0",
    "RISK_LEVEL":"0",
    "WITHIN_PACKAGE":""
   }
  ]
 },
 {
  "table":"SEOCLASSTX",
  "data":
  [
   {
    "CLSNAME":"ZCL_ETR_INVOICE_SAVE_JOB",
    "LANGU":"E",
    "DESCRIPT":"Invoice Users Job"
   }
  ]
 },
 {
  "table":"SEOMETAREL",
  "data":
  [
   {
    "CLSNAME":"ZCL_ETR_INVOICE_SAVE_JOB",
    "REFCLSNAME":"IF_APJ_DT_EXEC_OBJECT",
    "VERSION":1,
    "STATE":1,
    "AUTHOR":"",
    "CREATEDON":"2024-10-24",
    "CHANGEDBY":"",
    "CHANGEDON":"0000-00-00",
    "RELTYPE":1,
    "RELNAME":"",
    "EXPOSURE":2,
    "IMPFINAL":"",
    "IMPABSTRCT":"",
    "EDITORDER":1,
    "PARTIALLYIMP":""
   },
   {
    "CLSNAME":"ZCL_ETR_INVOICE_SAVE_JOB",
    "REFCLSNAME":"IF_APJ_RT_EXEC_OBJECT",
    "VERSION":1,
    "STATE":1,
    "AUTHOR":"",
    "CREATEDON":"2024-10-24",
    "CHANGEDBY":"",
    "CHANGEDON":"0000-00-00",
    "RELTYPE":1,
    "RELNAME":"",
    "EXPOSURE":2,
    "IMPFINAL":"",
    "IMPABSTRCT":"",
    "EDITORDER":2,
    "PARTIALLYIMP":""
   }
  ]
 },
 {
  "table":"TADIR",
  "data":
  [
   {
    "PGMID":"R3TR",
    "OBJECT":"CLAS",
    "OBJ_NAME":"ZCL_ETR_INVOICE_SAVE_JOB",
    "KORRNUM":"",
    "SRCSYSTEM":"...",
    "AUTHOR":"SAP_CUSTOMER",
    "SRCDEP":"",
    "DEVCLASS":"ZETR0",
    "GENFLAG":"",
    "EDTFLAG":"",
    "CPROJECT":" L",
    "MASTERLANG":"E",
    "VERSID":"",
    "PAKNOCHECK":"",
    "OBJSTABLTY":"",
    "COMPONENT":"",
    "CRELEASE":"",
    "DELFLAG":"",
    "TRANSLTTXT":"",
    "CREATED_ON":"2024-10-24",
    "CHECK_DATE":"2024-10-24",
    "CHECK_CFG":""
   }
  ]
 },
 {
  "table":"TMDIR",
  "data":
  [
   {
    "CLASSNAME":"ZCL_ETR_INVOICE_SAVE_JOB",
    "METHODINDX":0,
    "METHODNAME":" ",
    "FLAGS":0
   },
   {
    "CLASSNAME":"ZCL_ETR_INVOICE_SAVE_JOB",
    "METHODINDX":1,
    "METHODNAME":"IF_APJ_DT_EXEC_OBJECT~GET_PARAMETERS",
    "FLAGS":0
   },
   {
    "CLASSNAME":"ZCL_ETR_INVOICE_SAVE_JOB",
    "METHODINDX":2,
    "METHODNAME":"IF_APJ_RT_EXEC_OBJECT~EXECUTE",
    "FLAGS":0
   }
  ]
 },
 {
  "table":"TRDIR",
  "data":
  [
   {
    "NAME":"ZCL_ETR_INVOICE_SAVE_JOB======CCAU",
    "VARCL":"X",
    "DBAPL":"S",
    "DBNA":"D$",
    "SUBC":"I",
    "APPL":"S",
    "FIXPT":"X",
    "LDBNAME":"D$S",
    "UCCHECK":"X"
   },
   {
    "NAME":"ZCL_ETR_INVOICE_SAVE_JOB======CCDEF",
    "VARCL":"X",
    "DBAPL":"S",
    "DBNA":"D$",
    "SUBC":"I",
    "APPL":"S",
    "FIXPT":"X",
    "LDBNAME":"D$S",
    "UCCHECK":"X"
   },
   {
    "NAME":"ZCL_ETR_INVOICE_SAVE_JOB======CCIMP",
    "VARCL":"X",
    "DBAPL":"S",
    "DBNA":"D$",
    "SUBC":"I",
    "APPL":"S",
    "FIXPT":"X",
    "LDBNAME":"D$S",
    "UCCHECK":"X"
   },
   {
    "NAME":"ZCL_ETR_INVOICE_SAVE_JOB======CCMAC",
    "VARCL":"X",
    "DBAPL":"S",
    "DBNA":"D$",
    "SUBC":"I",
    "APPL":"S",
    "FIXPT":"X",
    "LDBNAME":"D$S",
    "UCCHECK":"X"
   },
   {
    "NAME":"ZCL_ETR_INVOICE_SAVE_JOB======CI",
    "VARCL":"X",
    "DBAPL":"S",
    "DBNA":"D$",
    "SUBC":"I",
    "APPL":"S",
    "FIXPT":"X",
    "LDBNAME":"D$S",
    "UCCHECK":"X"
   },
   {
    "NAME":"ZCL_ETR_INVOICE_SAVE_JOB======CM001",
    "VARCL":"X",
    "DBAPL":"S",
    "DBNA":"D$",
    "SUBC":"I",
    "APPL":"S",
    "FIXPT":"X",
    "LDBNAME":"D$S",
    "UCCHECK":"X"
   },
   {
    "NAME":"ZCL_ETR_INVOICE_SAVE_JOB======CM002",
    "VARCL":"X",
    "DBAPL":"S",
    "DBNA":"D$",
    "SUBC":"I",
    "APPL":"S",
    "FIXPT":"X",
    "LDBNAME":"D$S",
    "UCCHECK":"X"
   },
   {
    "NAME":"ZCL_ETR_INVOICE_SAVE_JOB======CO",
    "VARCL":"X",
    "DBAPL":"S",
    "DBNA":"D$",
    "SUBC":"I",
    "APPL":"S",
    "FIXPT":"X",
    "LDBNAME":"D$S",
    "UCCHECK":"X"
   },
   {
    "NAME":"ZCL_ETR_INVOICE_SAVE_JOB======CP",
    "EDTX":"X",
    "VARCL":"X",
    "DBAPL":"S",
    "DBNA":"D$",
    "SUBC":"K",
    "APPL":"S",
    "FIXPT":"X",
    "LDBNAME":"D$S",
    "UCCHECK":"5"
   },
   {
    "NAME":"ZCL_ETR_INVOICE_SAVE_JOB======CT",
    "DBAPL":"S",
    "DBNA":"D$",
    "SUBC":"I",
    "APPL":"S",
    "FIXPT":"X",
    "LDBNAME":"D$S",
    "UCCHECK":"X"
   },
   {
    "NAME":"ZCL_ETR_INVOICE_SAVE_JOB======CU",
    "VARCL":"X",
    "DBAPL":"S",
    "DBNA":"D$",
    "SUBC":"I",
    "APPL":"S",
    "FIXPT":"X",
    "LDBNAME":"D$S",
    "UCCHECK":"X"
   }
  ]
 }
]