[
 {
  "table":"DDDDLSRC",
  "data":
  [
   {
    "DDLNAME":"ZETR_DDL_I_DLVRESP_SELECTION",
    "AS4LOCAL":"N",
    "AS4USER":"SAP_CUSTOMER",
    "AS4DATE":"0000-00-00",
    "AS4TIME":"00:00:00",
    "SOURCE":"@EndUserText.label: 'Delivery Response Selection'\r\ndefine abstract entity zetr_ddl_i_dlvresp_selection\r\n  //  with parameters parameter_name : parameter_type\r\n{\r\n  @UI.defaultValue : #( 'ELEMENT_OF_REFERENCED_ENTITY: DocumentDate')\r\n  DeliveryDate      : zetr_e_dlvdt;\r\n  DeliveryTime      : zetr_e_dlvtm;\r\n  ReceiverFirstName : zetr_e_recfn;\r\n  ReceiverLastName  : zetr_e_recln;\r\n  Notes             : zetr_e_notes;\r\n}\r\n/*+[internal] {\n\"BASEINFO\":\n{\n\"FROM\":\n[],\n\"ASSOCIATED\":\n[],\n\"BASE\":\n[],\n\"ANNO_REF\":\n[],\n\"SCALAR_FUNCTION\":\n[],\n\"VERSION\":0,\n\"ANNOREF_EVALUATION_ERROR\":\"\"\n}\n}*/",
    "PARENTNAME":"",
    "ACTFLAG":"",
    "CHGFLAG":",4",
    "SOURCE_TYPE":"A",
    "SOURCE_ORIGIN":"0",
    "ABAP_LANGUAGE_VERSION":"5"
   }
  ]
 },
 {
  "table":"DDDDLSRC02BT",
  "data":
  [
   {
    "DDLNAME":"ZETR_DDL_I_DLVRESP_SELECTION",
    "STRUCOBJN":"ZETR_DDL_I_DLVRESP_SELECTION",
    "DDLANGUAGE":"E",
    "AS4LOCAL":"N",
    "DDTEXT":"Delivery Response Selection"
   }
  ]
 },
 {
  "table":"DDDDLSRC03NT",
  "data":
  [
   {
    "DDLNAME":"ZETR_DDL_I_DLVRESP_SELECTION",
    "STRUCOBJN":"ZETR_DDL_I_DLVRESP_SELECTION",
    "NODENAME":".NODE1",
    "DDLANGUAGE":"E",
    "AS4LOCAL":"N",
    "FIELDNAME":"DELIVERYDATE",
    "DEPTH":0,
    "DDTEXT":"Delivery date",
    "FIELDLABEL":"",
    "QUICKINFO":""
   },
   {
    "DDLNAME":"ZETR_DDL_I_DLVRESP_SELECTION",
    "STRUCOBJN":"ZETR_DDL_I_DLVRESP_SELECTION",
    "NODENAME":".NODE1",
    "DDLANGUAGE":"E",
    "AS4LOCAL":"N",
    "FIELDNAME":"DELIVERYTIME",
    "DEPTH":0,
    "DDTEXT":"Delivery time",
    "FIELDLABEL":"",
    "QUICKINFO":""
   },
   {
    "DDLNAME":"ZETR_DDL_I_DLVRESP_SELECTION",
    "STRUCOBJN":"ZETR_DDL_I_DLVRESP_SELECTION",
    "NODENAME":".NODE1",
    "DDLANGUAGE":"E",
    "AS4LOCAL":"N",
    "FIELDNAME":"NOTES",
    "DEPTH":0,
    "DDTEXT":"Note",
    "FIELDLABEL":"",
    "QUICKINFO":""
   },
   {
    "DDLNAME":"ZETR_DDL_I_DLVRESP_SELECTION",
    "STRUCOBJN":"ZETR_DDL_I_DLVRESP_SELECTION",
    "NODENAME":".NODE1",
    "DDLANGUAGE":"E",
    "AS4LOCAL":"N",
    "FIELDNAME":"RECEIVERFIRSTNAME",
    "DEPTH":0,
    "DDTEXT":"Receiver first name",
    "FIELDLABEL":"",
    "QUICKINFO":""
   },
   {
    "DDLNAME":"ZETR_DDL_I_DLVRESP_SELECTION",
    "STRUCOBJN":"ZETR_DDL_I_DLVRESP_SELECTION",
    "NODENAME":".NODE1",
    "DDLANGUAGE":"E",
    "AS4LOCAL":"N",
    "FIELDNAME":"RECEIVERLASTNAME",
    "DEPTH":0,
    "DDTEXT":"Receiver last name",
    "FIELDLABEL":"",
    "QUICKINFO":""
   }
  ]
 },
 {
  "table":"DDDDLSRCT",
  "data":
  [
   {
    "DDLNAME":"ZETR_DDL_I_DLVRESP_SELECTION",
    "DDLANGUAGE":"E",
    "AS4LOCAL":"N",
    "DDTEXT":"Delivery Response Selection"
   }
  ]
 },
 {
  "table":"DDFIELDANNO",
  "data":
  [
   {
    "STRUCOBJN":"ZETR_DDL_I_DLVRESP_SELECTION",
    "LFIELDNAME":"DELIVERYDATE",
    "NAME":"UI",
    "POSITION":1,
    "VALUE":""
   },
   {
    "STRUCOBJN":"ZETR_DDL_I_DLVRESP_SELECTION",
    "LFIELDNAME":"DELIVERYDATE",
    "NAME":"UI.DEFAULTVALUE",
    "POSITION":2,
    "VALUE":"#( 'ELEMENT_OF_REFERENCED_ENTITY: DocumentDate')"
   }
  ]
 },
 {
  "table":"DDHEADANNO",
  "data":
  [
   {
    "STRUCOBJN":"ZETR_DDL_I_DLVRESP_SELECTION",
    "NAME":"ENDUSERTEXT",
    "POSITION":1,
    "VALUE":""
   },
   {
    "STRUCOBJN":"ZETR_DDL_I_DLVRESP_SELECTION",
    "NAME":"ENDUSERTEXT.LABEL",
    "POSITION":2,
    "VALUE":"'Delivery Response Selection'"
   }
  ]
 },
 {
  "table":"DDLDEPENDENCY",
  "data":
  [
   {
    "DDLNAME":"ZETR_DDL_I_DLVRESP_SELECTION",
    "OBJECTNAME":"ZETR_DDL_I_DLVRESP_SELECTION",
    "STATE":"N",
    "OBJECTTYPE":"STOB"
   }
  ]
 },
 {
  "table":"TADIR",
  "data":
  [
   {
    "PGMID":"R3TR",
    "OBJECT":"DDLS",
    "OBJ_NAME":"ZETR_DDL_I_DLVRESP_SELECTION",
    "KORRNUM":"",
    "SRCSYSTEM":"...",
    "AUTHOR":"SAP_CUSTOMER",
    "SRCDEP":"",
    "DEVCLASS":"ZETR0",
    "GENFLAG":"",
    "EDTFLAG":"",
    "CPROJECT":" L",
    "MASTERLANG":"E",
    "VERSID":"",
    "PAKNOCHECK":"",
    "OBJSTABLTY":"",
    "COMPONENT":"",
    "CRELEASE":"",
    "DELFLAG":"",
    "TRANSLTTXT":"",
    "CREATED_ON":"2024-01-24",
    "CHECK_DATE":"2024-01-24",
    "CHECK_CFG":""
   }
  ]
 }
]